acrome_premium-1.0.7.dist-info/licenses/LICENSE
premium/__init__.py
premium/blue.py
premium/osModules.py
acrome_premium-1.0.7.dist-info/METADATA
acrome_premium-1.0.7.dist-info/WHEEL
acrome_premium-1.0.7.dist-info/top_level.txt
acrome_premium-1.0.7.dist-info/RECORD
